LICENSE
README.md
setup.py
trident_models_package/__init__.py
trident_models_package/models.py
trident_models_package.egg-info/PKG-INFO
trident_models_package.egg-info/SOURCES.txt
trident_models_package.egg-info/dependency_links.txt
trident_models_package.egg-info/top_level.txt